udata_dl/__init__.py
udata_dl/cli.py
udata_dl/downloader.py
udata_dl-0.4.6.dist-info/METADATA
udata_dl-0.4.6.dist-info/WHEEL
udata_dl-0.4.6.dist-info/entry_points.txt
udata_dl-0.4.6.dist-info/licenses/LICENSE
udata_dl-0.4.6.dist-info/RECORD
